{
    "hobby": [
        "网瘾",
        "小学生",
        "minecraft",
        "node",
        "跑者",
        "前端",
        "骑行"
    ],
    "line": [
        {
            "time": "2024.9",
            "thing": "筹备大学生创新创业项目"
        },
        {
            "time": "2024.7",
            "thing": "注册域名 yydsa.top"
        },
        {
            "time": "2024.5",
            "thing": "有了 node.js，现在前后端同时开发"
        },
        {
            "time": "2024.3",
            "thing": "尝试学习 C++，发现无用武之地"
        },
        {
            "time": "...",
            "thing": "..."
        },
        {
            "time": "2023.6",
            "thing": "参加了马拉松"
        },
        {
            "time": "2023.2",
            "thing": "参加 Web 技能大赛"
        },
        {
            "time": "2022.12",
            "thing": "尝试开发一个小项目"
        },
        {
            "time": "2022.9",
            "thing": "开始学习 Vue"
        },
        {
            "time": "2022.8",
            "thing": "开始学习前端"
        }
    ]
}